odoo/addons/mrp_bom_tag/README.rst
odoo/addons/mrp_bom_tag/__init__.py
odoo/addons/mrp_bom_tag/__manifest__.py
odoo/addons/mrp_bom_tag/demo/mrp_bom_tag.xml
odoo/addons/mrp_bom_tag/i18n/fr.po
odoo/addons/mrp_bom_tag/i18n/it.po
odoo/addons/mrp_bom_tag/i18n/mrp_bom_tag.pot
odoo/addons/mrp_bom_tag/models/__init__.py
odoo/addons/mrp_bom_tag/models/mrp_bom.py
odoo/addons/mrp_bom_tag/models/mrp_bom_tag.py
odoo/addons/mrp_bom_tag/readme/CONFIGURE.rst
odoo/addons/mrp_bom_tag/readme/CONTRIBUTORS.rst
odoo/addons/mrp_bom_tag/readme/DESCRIPTION.rst
odoo/addons/mrp_bom_tag/security/ir.model.access.csv
odoo/addons/mrp_bom_tag/security/ir_rule.xml
odoo/addons/mrp_bom_tag/static/description/bom_tag_configuration.png
odoo/addons/mrp_bom_tag/static/description/bom_with_tag.png
odoo/addons/mrp_bom_tag/static/description/icon.png
odoo/addons/mrp_bom_tag/static/description/index.html
odoo/addons/mrp_bom_tag/tests/__init__.py
odoo/addons/mrp_bom_tag/tests/test_bom_tag.py
odoo/addons/mrp_bom_tag/views/view_mrp_bom.xml
odoo/addons/mrp_bom_tag/views/view_mrp_bom_tag.xml
odoo_addon_mrp_bom_tag-16.0.1.2.0.dist-info/METADATA
odoo_addon_mrp_bom_tag-16.0.1.2.0.dist-info/WHEEL
odoo_addon_mrp_bom_tag-16.0.1.2.0.dist-info/top_level.txt
odoo_addon_mrp_bom_tag-16.0.1.2.0.dist-info/RECORD
